Metadata-Version: 1.1
Name: spider-task-scheduler
Version: 1.0.9
Summary: A redis task scheduler
Home-page: https://github.com/tangknives
Author: Joe Yuan
Author-email: tangknives@qq.com
License: MIT
Keywords: hive client python
Platform: UNKNOWN
Classifier: Development Status :: 4 - Beta
Classifier: Intended Audience :: Developers
Classifier: Topic :: Software Development :: Build Tools
Classifier: License :: OSI Approved :: MIT License
Classifier: Programming Language :: Python :: 2.6
Classifier: Programming Language :: Python :: 2.7
Classifier: Programming Language :: Python :: 3
Classifier: Programming Language :: Python :: 3.3
Classifier: Programming Language :: Python :: 3.4
Classifier: Programming Language :: Python :: 3.5
